stripe_hooks/__init__.py
stripe_hooks/__main__.py
stripe_hooks/app.py
stripe_hooks/bootstrap.py
stripe_hooks/helpers.py
stripe_hooks/hook.py
stripe_hooks/mail.py
stripe_hooks/parser.py
stripe_hooks-0.1.dist-info/METADATA
stripe_hooks-0.1.dist-info/RECORD
stripe_hooks-0.1.dist-info/WHEEL
stripe_hooks-0.1.dist-info/entry_points.txt
stripe_hooks-0.1.dist-info/top_level.txt
