Metadata-Version: 2.1
Name: stripe-hooks
Version: 0.1
Summary: A low-configuration service for sending notifications andreceipts based on Stripe webhooks.
Home-page: https://github.com/tolteck/stripe-hooks
Author: Hoël Iris
Author-email: hoel.iris@gmail.com
License: UNKNOWN
Platform: UNKNOWN
Classifier: Programming Language :: Python :: 3
Classifier: License :: OSI Approved :: MIT License
Classifier: Operating System :: POSIX :: Linux
Requires-Dist: Flask (>=1.0.2)
Requires-Dist: stripe (>=2.4.0)
